schelp_watch/__init__.py
schelp_watch/__main__.py
schelp_watch-0.0.3.dist-info/METADATA
schelp_watch-0.0.3.dist-info/WHEEL
schelp_watch-0.0.3.dist-info/entry_points.txt
schelp_watch-0.0.3.dist-info/RECORD
