Metadata-Version: 2.4
Name: schelp-watch
Version: 0.0.3
Summary: Live preview and autoreload for editing SuperCollider HelpFiles.
Project-URL: Homepage, https://github.com/elgiano/schelp-watch
Project-URL: Issues, https://github.com/elgiano/schelp-watch/issues
Author-email: Gianluca Elia <dev@gianlucaelia.eu>
License-Expression: Unlicense
Requires-Python: >=3.8
Requires-Dist: watchfiles
